agents/__init__.py
agents/coordinator.py
agents/diagnostician.py
agents/neurologist.py
agents/pharmacist.py
agents/pharmacist_methods.py
agents/surgeon.py
benchmarks/__init__.py
benchmarks/community_package.py
benchmarks/dataset_utils.py
benchmarks/judges.py
benchmarks/red_team.py
benchmarks/skill_tests.py
oumi_hospital/__init__.py
oumi_hospital/cli.py
oumi_hospital/core.py
oumi_hospital/demo.py
oumi_hospital/agents/__init__.py
oumi_hospital/agents/coordinator.py
oumi_hospital/agents/diagnostician.py
oumi_hospital/agents/neurologist.py
oumi_hospital/agents/pharmacist.py
oumi_hospital/agents/pharmacist_methods.py
oumi_hospital/agents/surgeon.py
oumi_hospital/benchmarks/__init__.py
oumi_hospital/benchmarks/community_package.py
oumi_hospital/benchmarks/dataset_utils.py
oumi_hospital/benchmarks/judges.py
oumi_hospital/benchmarks/red_team.py
oumi_hospital/benchmarks/skill_tests.py
oumi_hospital/utils/__init__.py
oumi_hospital/utils/console.py
oumi_hospital/utils/logging_config.py
oumi_hospital/utils/oumi_integration.py
oumi_hospital-1.0.1.dist-info/licenses/LICENSE
utils/__init__.py
utils/console.py
utils/logging_config.py
utils/oumi_integration.py
oumi_hospital-1.0.1.dist-info/METADATA
oumi_hospital-1.0.1.dist-info/WHEEL
oumi_hospital-1.0.1.dist-info/entry_points.txt
oumi_hospital-1.0.1.dist-info/top_level.txt
oumi_hospital-1.0.1.dist-info/RECORD
