Metadata-Version: 2.4
Name: oumi-hospital
Version: 1.0.1
Summary: 🏥 LLM-Powered Multi-Agent AI Model Repair System - Revolutionary autonomous diagnosis, treatment, and healing of unsafe AI models
Author-email: Oumi Hospital Team <contact@oumi-hospital.ai>
License: MIT
Project-URL: Homepage, https://github.com/soumyacodes007/infinity-hacks
Project-URL: Repository, https://github.com/soumyacodes007/infinity-hacks
Project-URL: Documentation, https://github.com/soumyacodes007/infinity-hacks/blob/master/README.md
Project-URL: Bug Tracker, https://github.com/soumyacodes007/infinity-hacks/issues
Keywords: ai,llm,model-repair,safety,alignment,oumi
Classifier: Development Status :: 3 - Alpha
Classifier: Intended Audience :: Developers
Classifier: Intended Audience :: Science/Research
Classifier: License :: OSI Approved :: MIT License
Classifier: Programming Language :: Python :: 3
Classifier: Programming Language :: Python :: 3.10
Classifier: Programming Language :: Python :: 3.11
Classifier: Programming Language :: Python :: 3.12
Classifier: Topic :: Scientific/Engineering :: Artificial Intelligence
Classifier: Topic :: Software Development :: Libraries :: Python Modules
Requires-Python: >=3.8
License-File: LICENSE
Requires-Dist: groq>=0.4.0
Requires-Dist: rich>=13.0.0
Requires-Dist: click>=8.0.0
Requires-Dist: pyyaml>=6.0.0
Requires-Dist: transformers>=4.30.0
Requires-Dist: torch>=2.0.0
Requires-Dist: datasets>=2.0.0
Requires-Dist: pandas>=2.0.0
Requires-Dist: numpy>=1.24.0
Requires-Dist: tqdm>=4.65.0
Requires-Dist: jinja2>=3.0.0
Requires-Dist: python-dotenv>=1.0.0
Provides-Extra: dev
Requires-Dist: pytest>=7.0.0; extra == "dev"
Requires-Dist: pytest-cov>=4.0.0; extra == "dev"
Requires-Dist: black>=23.0.0; extra == "dev"
Requires-Dist: isort>=5.12.0; extra == "dev"
Requires-Dist: flake8>=6.0.0; extra == "dev"
Requires-Dist: mypy>=1.0.0; extra == "dev"
Dynamic: license-file
